get_changed_kustomize_overlays/__init__.py
get_changed_kustomize_overlays/__main__.py
get_changed_kustomize_overlays-0.1.3.dist-info/LICENSE
get_changed_kustomize_overlays-0.1.3.dist-info/METADATA
get_changed_kustomize_overlays-0.1.3.dist-info/WHEEL
get_changed_kustomize_overlays-0.1.3.dist-info/top_level.txt
get_changed_kustomize_overlays-0.1.3.dist-info/RECORD
