Metadata-Version: 2.1
Name: get-changed-kustomize-overlays
Version: 0.1.3
Summary: A tool that helps you to test only those kustomize overlays that were affected by a merge in your CI.
Home-page: https://github.com/galshi/get-changed-kustomize-overlays
Author: Gal Shinder
Author-email: galsh1304@gmail.com
License: UNKNOWN
Platform: UNKNOWN
Classifier: Programming Language :: Python :: 3
Classifier: License :: OSI Approved :: MIT License
Classifier: Operating System :: OS Independent
License-File: LICENSE
